start_jupyter_cm/__init__.py
start_jupyter_cm/command.py
start_jupyter_cm/gnome.py
start_jupyter_cm/linux.py
start_jupyter_cm/macos.py
start_jupyter_cm/utils.py
start_jupyter_cm/windows.py
start_jupyter_cm/icons/jupyter-qtconsole.ico
start_jupyter_cm/icons/jupyter-qtconsole.png
start_jupyter_cm/icons/jupyter.ico
start_jupyter_cm/icons/jupyter.png
start_jupyter_cm/prototype.workflow/Contents/Info.plist
start_jupyter_cm/prototype.workflow/Contents/document.wflow
start_jupyter_cm/tests/__init__.py
start_jupyter_cm/tests/test_command.py
start_jupyter_cm-2.3.2.dist-info/LICENSE
start_jupyter_cm-2.3.2.dist-info/METADATA
start_jupyter_cm-2.3.2.dist-info/WHEEL
start_jupyter_cm-2.3.2.dist-info/entry_points.txt
start_jupyter_cm-2.3.2.dist-info/top_level.txt
start_jupyter_cm-2.3.2.dist-info/RECORD
